mp_async_worker/__init__.py
mp_async_worker/async_priority_batch_worker.py
mp_async_worker/async_worker.py
mp_async_worker/worker.py
mp_async_worker-0.0.1.dist-info/METADATA
mp_async_worker-0.0.1.dist-info/WHEEL
mp_async_worker-0.0.1.dist-info/licenses/LICENCE
mp_async_worker-0.0.1.dist-info/RECORD
